pdm_conda-0.18.3.dist-info/METADATA
pdm_conda-0.18.3.dist-info/WHEEL
pdm_conda-0.18.3.dist-info/entry_points.txt
pdm_conda/__init__.py
pdm_conda/cli/__init__.py
pdm_conda/cli/commands/__init__.py
pdm_conda/cli/commands/add.py
pdm_conda/cli/commands/init.py
pdm_conda/cli/commands/install.py
pdm_conda/cli/commands/list.py
pdm_conda/cli/commands/lock.py
pdm_conda/cli/commands/remove.py
pdm_conda/cli/commands/update.py
pdm_conda/cli/commands/use.py
pdm_conda/cli/commands/venv/__init__.py
pdm_conda/cli/commands/venv/backends.py
pdm_conda/cli/commands/venv/create.py
pdm_conda/cli/commands/venv/list.py
pdm_conda/cli/commands/venv/utils.py
pdm_conda/cli/utils.py
pdm_conda/conda.py
pdm_conda/environments/__init__.py
pdm_conda/environments/conda.py
pdm_conda/environments/python.py
pdm_conda/hooks.py
pdm_conda/installers/__init__.py
pdm_conda/installers/manager.py
pdm_conda/installers/synchronizers.py
pdm_conda/mapping.py
pdm_conda/models/__init__.py
pdm_conda/models/__pycache__/candidates.cpython-310.pyc.281473776611248
pdm_conda/models/candidates.py
pdm_conda/models/conda.py
pdm_conda/models/config.py
pdm_conda/models/repositories.py
pdm_conda/models/requirements.py
pdm_conda/models/setup.py
pdm_conda/project/__init__.py
pdm_conda/project/core.py
pdm_conda/project/project_file.py
pdm_conda/resolver/__init__.py
pdm_conda/resolver/graph.py
pdm_conda/resolver/providers.py
pdm_conda/resolvers.py
pdm_conda/utils.py
pdm_conda-0.18.3.dist-info/RECORD
