Metadata-Version: 2.1
Name: pdm-conda
Version: 0.18.3
Summary: A PDM plugin to resolve/install/uninstall project dependencies with Conda
Keywords: pdm,plugin,conda
Author: Marcos Pastorini
License: MIT
Classifier: Programming Language :: Python :: 3
Classifier: Programming Language :: Python :: 3.10
Classifier: Programming Language :: Python :: 3.11
Classifier: Programming Language :: Python :: 3.12
Project-URL: Homepage, https://github.com/macro128/pdm-conda
Project-URL: Changelog, https://github.com/macro128/pdm-conda/blob/main/CHANGELOG.md
Requires-Python: <3.13,>=3.10
Requires-Dist: pdm==2.16.1
Requires-Dist: typing-extensions>=4.10.0
Requires-Dist: httpx>=0.27.0
